CHANGELOG.rst
LICENSE
MANIFEST.in
README.rst
requirements.txt
setup.py
aflak/AboutDialog.py
aflak/AboutDialog_ui.py
aflak/AstroHistogramLUTItem.py
aflak/AstroHistogramLUTWidget.py
aflak/AstroImageView.py
aflak/AstroImageView_ui.py
aflak/AstroWaveFormPlotWidget.py
aflak/FitsHeaderForm.py
aflak/FitsHeaderForm_ui.py
aflak/FitsHeaderWindow.py
aflak/FitsHeaderWindow_ui.py
aflak/MultiROI.py
aflak/WCSAxis.py
aflak/__init__.py
aflak/__main__.py
aflak/aflak.py
aflak/fits.py
aflak/functions.py
aflak/mainwindow.py
aflak/mainwindow_ui.py
aflak/settings.py
aflak.egg-info/PKG-INFO
aflak.egg-info/SOURCES.txt
aflak.egg-info/dependency_links.txt
aflak.egg-info/entry_points.txt
aflak.egg-info/requires.txt
aflak.egg-info/top_level.txt